.coveragerc
.mailmap
.testr.conf
AUTHORS
CONTRIBUTING.rst
ChangeLog
HACKING.rst
LICENSE
MANIFEST.in
README.rst
babel.cfg
openstack-common.conf
requirements.txt
setup.cfg
setup.py
test-requirements.txt
tox.ini
collectd_ceilometer/__init__.py
collectd_ceilometer/keystone_light.py
collectd_ceilometer/logger.py
collectd_ceilometer/plugin.py
collectd_ceilometer/sender.py
collectd_ceilometer/settings.py
collectd_ceilometer/singleton.py
collectd_ceilometer/units.py
collectd_ceilometer/writer.py
collectd_ceilometer/meters/__init__.py
collectd_ceilometer/meters/base.py
collectd_ceilometer/meters/libvirt.py
collectd_ceilometer/meters/storage.py
collectd_ceilometer/tests/__init__.py
collectd_ceilometer/tests/base.py
collectd_ceilometer/tests/test_collectd_ceilometer.py
collectd_ceilometer/tests/test_collectd_ceilometer_plugin.py
collectd_ceilometer/tests/test_config.py
collectd_ceilometer/tests/test_keystone_light.py
collectd_ceilometer/tests/test_plugin.py
collectd_ceilometer_plugin.egg-info/PKG-INFO
collectd_ceilometer_plugin.egg-info/SOURCES.txt
collectd_ceilometer_plugin.egg-info/dependency_links.txt
collectd_ceilometer_plugin.egg-info/not-zip-safe
collectd_ceilometer_plugin.egg-info/pbr.json
collectd_ceilometer_plugin.egg-info/requires.txt
collectd_ceilometer_plugin.egg-info/top_level.txt
devstack/plugin.sh
devstack/settings
devstack/libs/collectd
doc/source/conf.py
doc/source/contributing.rst
doc/source/index.rst
doc/source/installation.rst
doc/source/readme.rst
doc/source/usage.rst
tools/pretty_tox.sh